[
   {
      "field": "roundNumber",
      "name": "roundNumber",
      "type": "int",
      "concreteType": "int",
      "nullable": false,
      "collection": false,
      "jsonIgnore": false
   },
   {
      "field": "playerRoundResultCode",
      "name": "playerRoundResultCode",
      "type": "string",
      "concreteType": "string",
      "nullable": false,
      "collection": false,
      "jsonIgnore": false
   },
   {
      "field": "playerRoundScore",
      "name": "playerRoundScore",
      "type": "int",
      "concreteType": "int",
      "nullable": false,
      "collection": false,
      "jsonIgnore": false
   },
   {
      "field": "roundPar",
      "name": "roundPar",
      "type": "int",
      "concreteType": "int",
      "nullable": false,
      "collection": false,
      "jsonIgnore": false
   },
   {
      "field": "playerRoundToPar",
      "name": "playerRoundToPar",
      "type": "string",
      "concreteType": "string",
      "nullable": false,
      "collection": false,
      "jsonIgnore": false
   },
   {
      "field": "fairwaysHit",
      "name": "fairwaysHit",
      "type": "int",
      "concreteType": "int",
      "nullable": false,
      "collection": false,
      "jsonIgnore": false
   },
   {
      "field": "fairwaysHitRank",
      "name": "fairwaysHitRank",
      "type": "int",
      "concreteType": "int",
      "nullable": false,
      "collection": false,
      "jsonIgnore": false
   },
   {
      "field": "fairwaysAttempted",
      "name": "fairwaysAttempted",
      "type": "int",
      "concreteType": "int",
      "nullable": false,
      "collection": false,
      "jsonIgnore": false
   },
   {
      "field": "fairwaysHitPercentage",
      "name": "fairwaysHitPercentage",
      "type": "decimal",
      "concreteType": "decimal",
      "nullable": false,
      "collection": false,
      "jsonIgnore": false
   },
   {
      "field": "greensHit",
      "name": "greensHit",
      "type": "int",
      "concreteType": "int",
      "nullable": false,
      "collection": false,
      "jsonIgnore": false
   },
   {
      "field": "greensHitRank",
      "name": "greensHitRank",
      "type": "int",
      "concreteType": "int",
      "nullable": false,
      "collection": false,
      "jsonIgnore": false
   },
   {
      "field": "greensAttempted",
      "name": "greensAttempted",
      "type": "int",
      "concreteType": "int",
      "nullable": false,
      "collection": false,
      "jsonIgnore": false
   },
   {
      "field": "greensHitPercentage",
      "name": "greensHitPercentage",
      "type": "decimal",
      "concreteType": "decimal",
      "nullable": false,
      "collection": false,
      "jsonIgnore": false
   },
   {
      "field": "sandSaves",
      "name": "sandSaves",
      "type": "int",
      "concreteType": "int",
      "nullable": false,
      "collection": false,
      "jsonIgnore": false
   },
   {
      "field": "sandSavesRank",
      "name": "sandSavesRank",
      "type": "int",
      "concreteType": "int",
      "nullable": false,
      "collection": false,
      "jsonIgnore": false
   },
   {
      "field": "sandSavesAttempted",
      "name": "sandSavesAttempted",
      "type": "int",
      "concreteType": "int",
      "nullable": false,
      "collection": false,
      "jsonIgnore": false
   },
   {
      "field": "sandSavesHitPercentage",
      "name": "sandSavesHitPercentage",
      "type": "decimal",
      "concreteType": "decimal",
      "nullable": false,
      "collection": false,
      "jsonIgnore": false
   },
   {
      "field": "drivingDistance",
      "name": "drivingDistance",
      "type": "string",
      "concreteType": "string",
      "nullable": false,
      "collection": false,
      "jsonIgnore": false
   },
   {
      "field": "drivingDistanceRank",
      "name": "drivingDistanceRank",
      "type": "int",
      "concreteType": "int",
      "nullable": false,
      "collection": false,
      "jsonIgnore": false
   },
   {
      "field": "drivingDistanceAverage",
      "name": "drivingDistanceAverage",
      "type": "decimal",
      "concreteType": "decimal",
      "nullable": false,
      "collection": false,
      "jsonIgnore": false
   },
   {
      "field": "drivingDistanceAggregate",
      "name": "drivingDistanceAggregate",
      "type": "decimal",
      "concreteType": "decimal",
      "nullable": false,
      "collection": false,
      "jsonIgnore": false
   },
   {
      "field": "puttsHit",
      "name": "puttsHit",
      "type": "int",
      "concreteType": "int",
      "nullable": false,
      "collection": false,
      "jsonIgnore": false
   },
   {
      "field": "puttsHitRank",
      "name": "puttsHitRank",
      "type": "int",
      "concreteType": "int",
      "nullable": false,
      "collection": false,
      "jsonIgnore": false
   },
   {
      "field": "girPutts",
      "name": "girPutts",
      "type": "int",
      "concreteType": "int",
      "nullable": false,
      "collection": false,
      "jsonIgnore": false
   },
   {
      "field": "girPuttsAverage",
      "name": "girPuttsAverage",
      "type": "decimal",
      "concreteType": "decimal",
      "nullable": false,
      "collection": false,
      "jsonIgnore": false
   },
   {
      "field": "eaglesCount",
      "name": "eaglesCount",
      "type": "int",
      "concreteType": "int",
      "nullable": false,
      "collection": false,
      "jsonIgnore": false
   },
   {
      "field": "birdiesCount",
      "name": "birdiesCount",
      "type": "int",
      "concreteType": "int",
      "nullable": false,
      "collection": false,
      "jsonIgnore": false
   },
   {
      "field": "parsCount",
      "name": "parsCount",
      "type": "int",
      "concreteType": "int",
      "nullable": false,
      "collection": false,
      "jsonIgnore": false
   },
   {
      "field": "bogiesCount",
      "name": "bogiesCount",
      "type": "int",
      "concreteType": "int",
      "nullable": false,
      "collection": false,
      "jsonIgnore": false
   }
]
