[
   {
      "field": "id",
      "name": "id",
      "type": "int",
      "concreteType": "int",
      "nullable": false,
      "collection": false,
      "jsonIgnore": false
   },
   {
      "field": "code",
      "name": "code",
      "type": "string",
      "concreteType": "string",
      "nullable": false,
      "collection": false,
      "jsonIgnore": false
   },
   {
      "field": "name",
      "name": "name",
      "type": "string",
      "concreteType": "string",
      "nullable": false,
      "collection": false,
      "jsonIgnore": false
   },
   {
      "field": "year",
      "name": "year",
      "type": "int",
      "concreteType": "int",
      "nullable": false,
      "collection": false,
      "jsonIgnore": false
   },
   {
      "field": "cityName",
      "name": "cityName",
      "type": "string",
      "concreteType": "string",
      "nullable": false,
      "collection": false,
      "jsonIgnore": false
   },
   {
      "field": "stateName",
      "name": "stateName",
      "type": "string",
      "concreteType": "string",
      "nullable": false,
      "collection": false,
      "jsonIgnore": false
   },
   {
      "field": "countryName",
      "name": "countryName",
      "type": "string",
      "concreteType": "string",
      "nullable": false,
      "collection": false,
      "jsonIgnore": false
   },
   {
      "field": "startDate",
      "name": "startDate",
      "type": "DateTime",
      "concreteType": "DateTime",
      "nullable": false,
      "collection": false,
      "jsonIgnore": false
   },
   {
      "field": "endDate",
      "name": "endDate",
      "type": "DateTime",
      "concreteType": "DateTime",
      "nullable": false,
      "collection": false,
      "jsonIgnore": false
   },
   {
      "field": "tournamentNumber",
      "name": "tournamentNumber",
      "type": "int",
      "concreteType": "int",
      "nullable": false,
      "collection": false,
      "jsonIgnore": false
   },
   {
      "field": "roundCount",
      "name": "roundCount",
      "type": "int",
      "concreteType": "int",
      "nullable": false,
      "collection": false,
      "jsonIgnore": false
   },
   {
      "field": "purse",
      "name": "purse",
      "type": "decimal",
      "concreteType": "decimal",
      "nullable": false,
      "collection": false,
      "jsonIgnore": false
   },
   {
      "field": "winnerAccountId",
      "name": "winnerAccountId",
      "type": "int",
      "concreteType": "int",
      "nullable": false,
      "collection": false,
      "jsonIgnore": false
   },
   {
      "field": "winnerPlayerName",
      "name": "winnerPlayerName",
      "type": "string",
      "concreteType": "string",
      "nullable": false,
      "collection": false,
      "jsonIgnore": false
   },
   {
      "field": "winnerPrizeMoney",
      "name": "winnerPrizeMoney",
      "type": "decimal",
      "concreteType": "decimal",
      "nullable": false,
      "collection": false,
      "jsonIgnore": false
   },
   {
      "field": "winnerFinalStrokeCount",
      "name": "winnerFinalStrokeCount",
      "type": "int",
      "concreteType": "int",
      "nullable": false,
      "collection": false,
      "jsonIgnore": false
   },
   {
      "field": "winnerFinalToPar",
      "name": "winnerFinalToPar",
      "type": "int",
      "concreteType": "int",
      "nullable": false,
      "collection": false,
      "jsonIgnore": false
   },
   {
      "field": "runnerupAccountId",
      "name": "runnerupAccountId",
      "type": "string",
      "concreteType": "string",
      "nullable": false,
      "collection": false,
      "jsonIgnore": false
   },
   {
      "field": "runnerupPlayerName",
      "name": "runnerupPlayerName",
      "type": "string",
      "concreteType": "string",
      "nullable": false,
      "collection": false,
      "jsonIgnore": false
   },
   {
      "field": "runnerupPrizeMoney",
      "name": "runnerupPrizeMoney",
      "type": "string",
      "concreteType": "string",
      "nullable": false,
      "collection": false,
      "jsonIgnore": false
   },
   {
      "field": "runnerupFinalStrokeCount",
      "name": "runnerupFinalStrokeCount",
      "type": "string",
      "concreteType": "string",
      "nullable": false,
      "collection": false,
      "jsonIgnore": false
   },
   {
      "field": "runnerupFinalToPar",
      "name": "runnerupFinalToPar",
      "type": "string",
      "concreteType": "string",
      "nullable": false,
      "collection": false,
      "jsonIgnore": false
   },
   {
      "field": "didFinishContainPlayoff",
      "name": "didFinishContainPlayoff",
      "type": "bool",
      "concreteType": "bool",
      "nullable": false,
      "collection": false,
      "jsonIgnore": false
   },
   {
      "field": "countryAbbreviation",
      "name": "countryAbbreviation",
      "type": "string",
      "concreteType": "string",
      "nullable": false,
      "collection": false,
      "jsonIgnore": false
   },
   {
      "field": "stateAbbreviation",
      "name": "stateAbbreviation",
      "type": "string",
      "concreteType": "string",
      "nullable": false,
      "collection": false,
      "jsonIgnore": false
   },
   {
      "field": "tourName",
      "name": "tourName",
      "type": "string",
      "concreteType": "string",
      "nullable": false,
      "collection": false,
      "jsonIgnore": false
   },
   {
      "field": "isMajor",
      "name": "isMajor",
      "type": "bool",
      "concreteType": "bool",
      "nullable": false,
      "collection": false,
      "jsonIgnore": false
   },
   {
      "field": "isDomestic",
      "name": "isDomestic",
      "type": "bool",
      "concreteType": "bool",
      "nullable": false,
      "collection": false,
      "jsonIgnore": false
   },
   {
      "field": "isOfficialMoney",
      "name": "isOfficialMoney",
      "type": "bool",
      "concreteType": "bool",
      "nullable": false,
      "collection": false,
      "jsonIgnore": false
   },
   {
      "field": "isSolheimEligible",
      "name": "isSolheimEligible",
      "type": "bool",
      "concreteType": "bool",
      "nullable": false,
      "collection": false,
      "jsonIgnore": false
   },
   {
      "field": "isLegendTournament",
      "name": "isLegendTournament",
      "type": "bool",
      "concreteType": "bool",
      "nullable": false,
      "collection": false,
      "jsonIgnore": false
   },
   {
      "field": "fields",
      "name": "fields",
      "type": "IStatsAPI_TournamentField",
      "concreteType": "StatsAPI_TournamentField",
      "nullable": true,
      "collection": false,
      "jsonIgnore": false
   },
   {
      "field": "course",
      "name": "course",
      "type": "IStatsAPI_TournamentCourse",
      "concreteType": "StatsAPI_TournamentCourse",
      "nullable": true,
      "collection": false,
      "jsonIgnore": false
   }
]
